pandas_cat/__init__.py
pandas_cat/pandas_cat.py
pandas_cat/templates/default_0_1_3.tem
pandas_cat/templates/interactive/interactive.html
pandas_cat/templates/interactive/css/main.css
pandas_cat/templates/interactive/img/bar.svg
pandas_cat/templates/interactive/img/categories.svg
pandas_cat/templates/interactive/img/cols.svg
pandas_cat/templates/interactive/img/copy.svg
pandas_cat/templates/interactive/img/donut.svg
pandas_cat/templates/interactive/img/error.svg
pandas_cat/templates/interactive/img/hbar.svg
pandas_cat/templates/interactive/img/help.svg
pandas_cat/templates/interactive/img/interactive.svg
pandas_cat/templates/interactive/img/least.svg
pandas_cat/templates/interactive/img/left.svg
pandas_cat/templates/interactive/img/log.svg
pandas_cat/templates/interactive/img/missing.svg
pandas_cat/templates/interactive/img/moon.svg
pandas_cat/templates/interactive/img/most.svg
pandas_cat/templates/interactive/img/percentage.svg
pandas_cat/templates/interactive/img/pie.svg
pandas_cat/templates/interactive/img/print.svg
pandas_cat/templates/interactive/img/ram.svg
pandas_cat/templates/interactive/img/reverse.svg
pandas_cat/templates/interactive/img/right.svg
pandas_cat/templates/interactive/img/rows.svg
pandas_cat/templates/interactive/img/sort.svg
pandas_cat/templates/interactive/img/sun.svg
pandas_cat/templates/interactive/img/table.svg
pandas_cat/templates/interactive/js/main.js
pandas_cat/templates/interactive/sass/_attributes.scss
pandas_cat/templates/interactive/sass/_base.scss
pandas_cat/templates/interactive/sass/_box.scss
pandas_cat/templates/interactive/sass/_button.scss
pandas_cat/templates/interactive/sass/_correlations.scss
pandas_cat/templates/interactive/sass/_footer.scss
pandas_cat/templates/interactive/sass/_header.scss
pandas_cat/templates/interactive/sass/_layout.scss
pandas_cat/templates/interactive/sass/_minitable.scss
pandas_cat/templates/interactive/sass/_modal.scss
pandas_cat/templates/interactive/sass/_scrollbar.scss
pandas_cat-0.1.3.dist-info/LICENSE
pandas_cat-0.1.3.dist-info/METADATA
pandas_cat-0.1.3.dist-info/WHEEL
pandas_cat-0.1.3.dist-info/top_level.txt
pandas_cat-0.1.3.dist-info/RECORD
