Metadata-Version: 2.1
Name: pandas-cat
Version: 0.1.3
Summary: Pandas categorical profiling. Generates html profile report for categorical dataset. Also provides several handful functions.
Home-page: https://petrmasa.com/pandas-cat
Author: (C) Copyright 2022 - 2024 Petr Masa & LBC
Author-email: code@cleverminer.org
License: MIT
Classifier: Programming Language :: Python :: 3
Classifier: Development Status :: 4 - Beta
Classifier: License :: OSI Approved :: MIT License
Classifier: Operating System :: OS Independent
Requires-Python: >=3.8
License-File: LICENSE
Requires-Dist: numpy
Requires-Dist: pandas
Requires-Dist: seaborn
Requires-Dist: matplotlib
Requires-Dist: datasize
Requires-Dist: jinja2
Requires-Dist: cleverminer
Requires-Dist: scikit-learn
